{"comments":[{"_id":"08ecc5dc-ca97-4d34-81da-af297383cd62","created_at":"2019-03-02T20:22:20.972Z","updated_at":"2019-03-02T20:22:20.972Z","channel_id":"23161357","content_type":"video","content_id":"389178879","content_offset_seconds":11878.272,"commenter":{"display_name":"Meatloaph","_id":"25411838","name":"meatloaph","type":"user","bio":null,"created_at":"2011-10-12T05:14:15.961041Z","updated_at":"2019-03-10T03:41:35.496206Z","logo":"https://static-cdn.jtvnw.net/jtv_user_pictures/meatloaph-profile_image-b94be3f75b7f30f2-300x300.jpeg"},"source":"chat","state":"published","message":{"body":"Did you shit yourself? @LIRIK","fragments":[{"text":"Did you shit yourself? @LIRIK"}],"is_action":false,"user_color":"#FF69B4"},"more_replies":false},{"_id":"1d72adfd-db80-4a50-bebb-9bb8e38311c1","created_at":"2019-03-02T20:22:21.136Z","updated_at":"2019-03-02T20:22:21.136Z","channel_id":"23161357","content_type":"video","content_id":"389178879","content_offset_seconds":11878.436,"commenter":{"display_name":"Blueberry_kush","_id":"81793758","name":"blueberry_kush","type":"user","bio":null,"created_at":"2015-02-04T17:04:25.627585Z","updated_at":"2019-02-19T17:49:50.151273Z","logo":"https://static-cdn.jtvnw.net/user-default-pictures/cd618d3e-f14d-4960-b7cf-094231b04735-profile_image-300x300.jpg"},"source":"chat","state":"published","message":{"body":"Lol","fragments":[{"text":"Lol"}],"is_action":false,"user_badges":[{"_id":"subscriber","version":"0"},{"_id":"premium","version":"1"}]},"more_replies":false},{"_id":"b1dedb23-c1d9-461c-8a8f-4090a03a94c0","created_at":"2019-03-02T20:22:21.277Z","updated_at":"2019-03-02T20:22:21.277Z","channel_id":"23161357","content_type":"video","content_id":"389178879","content_offset_seconds":11878.577,"commenter":{"display_name":"ballsdangling","_id":"136927634","name":"ballsdangling","type":"user","bio":null,"created_at":"2016-10-12T19:58:07.579977Z","updated_at":"2018-09-24T20:31:57.118493Z","logo":"https://static-cdn.jtvnw.net/user-default-pictures/cd618d3e-f14d-4960-b7cf-094231b04735-profile_image-300x300.jpg"},"source":"chat","state":"published","message":{"body":"FailFish","emoticons":[{"_id":"360","begin":0,"end":7}],"fragments":[{"text":"FailFish","emoticon":{"emoticon_id":"360","emoticon_set_id":""}}],"is_action":false},"more_replies":false},{"_id":"7cc40273-296a-429c-83e4-55361d9ea0e8","created_at":"2019-03-02T20:22:21.342Z","updated_at":"2019-03-02T20:22:21.342Z","channel_id":"23161357","content_type":"video","content_id":"389178879","content_offset_seconds":11878.642,"commenter":{"display_name":"Mak_9","_id":"117397550","name":"mak_9","type":"user","bio":null,"created_at":"2016-02-29T22:25:38.619457Z","updated_at":"2019-03-09T21:25:48.257357Z","logo":"https://static-cdn.jtvnw.net/jtv_user_pictures/mak_9-profile_image-52c97b77a3c29f51-300x300.jpeg"},"source":"chat","state":"published","message":{"body":"turn shorty down WutFace","emoticons":[{"_id":"28087","begin":17,"end":23}],"fragments":[{"text":"turn shorty down "},{"text":"WutFace","emoticon":{"emoticon_id":"28087","emoticon_set_id":""}}],"is_action":false,"user_color":"#B22222"},"more_replies":false},{"_id":"7b6eb532-d061-498f-a989-191c1d6cd44d","created_at":"2019-03-02T20:22:22.021Z","updated_at":"2019-03-02T20:22:22.021Z","channel_id":"23161357","content_type":"video","content_id":"389178879","content_offset_seconds":11879.321,"commenter":{"display_name":"mamamia53","_id":"45041513","name":"mamamia53","type":"user","bio":null,"created_at":"2013-06-21T21:36:48.987851Z","updated_at":"2019-02-28T17:05:16.174682Z","logo":"https://static-cdn.jtvnw.net/user-default-pictures/b83b1794-7df9-4878-916c-88c2ad2e4f9f-profile_image-300x300.jpg"},"source":"chat","state":"published","message":{"body":"@LIRIK we heard that you farted","fragments":[{"text":"@LIRIK we heard that you farted"}],"is_action":false,"user_color":"#FF0000"},"more_replies":false},{"_id":"30df4c52-7501-43e0-917f-84a1d0ae26b3","created_at":"2019-03-02T20:22:22.483Z","updated_at":"2019-03-02T20:22:22.483Z","channel_id":"23161357","content_type":"video","content_id":"389178879","content_offset_seconds":11879.783,"commenter":{"display_name":"LiftAir","_id":"66401596","name":"liftair","type":"user","bio":null,"created_at":"2014-07-15T16:17:14.270136Z","updated_at":"2019-02-19T20:04:25.777176Z","logo":"https://static-cdn.jtvnw.net/user-default-pictures/49988c7b-57bc-4dee-bd4f-6df4ad215d3a-profile_image-300x300.jpg"},"source":"chat","state":"published","message":{"body":"D:","fragments":[{"text":"D:"}],"is_action":false,"user_badges":[{"_id":"subscriber","version":"12"}],"user_color":"#5F9EA0"},"more_replies":false},{"_id":"da4660c7-2625-4b5e-9cc7-0c8089f133c3","created_at":"2019-03-02T20:22:23.258Z","updated_at":"2019-03-02T20:22:23.258Z","channel_id":"23161357","content_type":"video","content_id":"389178879","content_offset_seconds":11880.558,"commenter":{"display_name":"cryptoj","_id":"105602477","name":"cryptoj","type":"user","bio":null,"created_at":"2015-10-29T20:49:00.949058Z","updated_at":"2019-03-06T14:19:26.915856Z","logo":"https://static-cdn.jtvnw.net/user-default-pictures/27103734-3cda-44d6-a384-f2ab71e4bb85-profile_image-300x300.jpg"},"source":"chat","state":"published","message":{"body":"Please tell me someone clipped that!","fragments":[{"text":"Please tell me someone clipped that!"}],"is_action":false,"user_badges":[{"_id":"premium","version":"1"}],"user_color":"#8A2BE2"},"more_replies":false},{"_id":"95c96470-b48e-493d-8ca1-eb97d8b886b3","created_at":"2019-03-02T20:22:23.476Z","updated_at":"2019-03-02T20:22:23.476Z","channel_id":"23161357","content_type":"video","content_id":"389178879","content_offset_seconds":11880.776,"commenter":{"display_name":"Papalotapuss","_id":"108978387","name":"papalotapuss","type":"user","bio":"Wadu Hek?","created_at":"2015-12-07T19:46:32.548627Z","updated_at":"2019-03-09T03:56:28.023883Z","logo":"https://static-cdn.jtvnw.net/jtv_user_pictures/c02d4902-6875-483b-aef0-39356aca2b4c-profile_image-300x300.png"},"source":"chat","state":"published","message":{"body":"ppJedi lirikDD ppJedi lirikDD ppJedi lirikDD ppJedi lirikDD ppJedi lirikDD ppJedi lirikDD ppJedi lirikDD ppJedi lirikDD","fragments":[{"text":"ppJedi lirikDD ppJedi lirikDD ppJedi lirikDD ppJedi lirikDD ppJedi lirikDD ppJedi lirikDD ppJedi lirikDD ppJedi lirikDD"}],"is_action":false,"user_badges":[{"_id":"subscriber","version":"6"},{"_id":"premium","version":"1"}],"user_color":"#DAA520"},"more_replies":false},{"_id":"0737977c-60b2-4fb2-b042-0fc528bc3b83","created_at":"2019-03-02T20:22:23.714Z","updated_at":"2019-03-02T20:22:23.714Z","channel_id":"23161357","content_type":"video","content_id":"389178879","content_offset_seconds":11881.014,"commenter":{"display_name":"Murdoc_QB","_id":"57646104","name":"murdoc_qb","type":"user","bio":null,"created_at":"2014-02-24T17:43:29.176852Z","updated_at":"2019-03-10T12:58:19.419564Z","logo":"https://static-cdn.jtvnw.net/jtv_user_pictures/murdoc_qb-profile_image-97446f2630edaad8-300x300.jpeg"},"source":"chat","state":"published","message":{"body":"ppJedi lirikDD ppJedi lirikDD ppJedi lirikDD ppJedi lirikDD ppJedi lirikDD ppJedi lirikDD ppJedi lirikDD ppJedi lirikDD ppJedi lirikDD ppJedi lirikDD ppJedi lirikDD ppJedi lirikDD ppJedi lirikDD ppJedi lirikDD ppJedi lirikDD ppJedi lirikDD","fragments":[{"text":"ppJedi lirikDD ppJedi lirikDD ppJedi lirikDD ppJedi lirikDD ppJedi lirikDD ppJedi lirikDD ppJedi lirikDD ppJedi lirikDD ppJedi lirikDD ppJedi lirikDD ppJedi lirikDD ppJedi lirikDD ppJedi lirikDD ppJedi lirikDD ppJedi lirikDD ppJedi lirikDD"}],"is_action":false,"user_badges":[{"_id":"subscriber","version":"12"},{"_id":"premium","version":"1"}],"user_color":"#00CCFF"},"more_replies":false},{"_id":"aae2ef9a-44c3-4e5e-88e9-537f56244f81","created_at":"2019-03-02T20:22:23.968Z","updated_at":"2019-03-02T20:22:23.968Z","channel_id":"23161357","content_type":"video","content_id":"389178879","content_offset_seconds":11881.268,"commenter":{"display_name":"Angeroth","_id":"66889618","name":"angeroth","type":"user","bio":null,"created_at":"2014-07-21T17:31:06.940252Z","updated_at":"2019-03-09T23:42:51.891099Z","logo":"https://static-cdn.jtvnw.net/jtv_user_pictures/angeroth-profile_image-742e5a149f9e441b-300x300.jpeg"},"source":"chat","state":"published","message":{"body":"NotLeeroy ikr lirikC how are you doing lirikH lirikHUG","emoticons":[{"_id":"1498561","begin":39,"end":44},{"_id":"1498657","begin":46,"end":53}],"fragments":[{"text":"NotLeeroy ikr lirikC how are you doing "},{"text":"lirikH","emoticon":{"emoticon_id":"1498561","emoticon_set_id":""}},{"text":" "},{"text":"lirikHUG","emoticon":{"emoticon_id":"1498657","emoticon_set_id":""}}],"is_action":false,"user_badges":[{"_id":"subscriber","version":"48"}],"user_color":"#FF0000"},"more_replies":false},{"_id":"27e95485-8b46-457a-b6b6-7559efafad46","created_at":"2019-03-02T20:22:24.903Z","updated_at":"2019-03-02T20:22:24.903Z","channel_id":"23161357","content_type":"video","content_id":"389178879","content_offset_seconds":11882.203,"commenter":{"display_name":"basil94","_id":"120723481","name":"basil94","type":"user","bio":null,"created_at":"2016-04-02T15:48:00.234428Z","updated_at":"2018-11-02T19:42:00.599478Z","logo":"https://static-cdn.jtvnw.net/user-default-pictures/cd618d3e-f14d-4960-b7cf-094231b04735-profile_image-300x300.jpg"},"source":"chat","state":"published","message":{"body":"PJSalt PJSalt PJSalt PJSalt","emoticons":[{"_id":"36","begin":0,"end":5},{"_id":"36","begin":7,"end":12},{"_id":"36","begin":14,"end":19},{"_id":"36","begin":21,"end":26}],"fragments":[{"text":"PJSalt","emoticon":{"emoticon_id":"36","emoticon_set_id":""}},{"text":" "},{"text":"PJSalt","emoticon":{"emoticon_id":"36","emoticon_set_id":""}},{"text":" "},{"text":"PJSalt","emoticon":{"emoticon_id":"36","emoticon_set_id":""}},{"text":" "},{"text":"PJSalt","emoticon":{"emoticon_id":"36","emoticon_set_id":""}}],"is_action":false},"more_replies":false},{"_id":"b208d348-6dda-471f-959f-236f8eb3fce5","created_at":"2019-03-02T20:22:27.231Z","updated_at":"2019-03-02T20:22:27.231Z","channel_id":"23161357","content_type":"video","content_id":"389178879","content_offset_seconds":11884.531,"commenter":{"display_name":"kingfreak","_id":"2234025","name":"kingfreak","type":"user","bio":null,"created_at":"2008-10-22T03:47:27.984179Z","updated_at":"2019-02-14T18:02:01.298079Z","logo":"https://static-cdn.jtvnw.net/jtv_user_pictures/kingfreak-profile_image-c7bb5be12f0a99e3-300x300.png"},"source":"chat","state":"published","message":{"body":"WutFace WutFace WutFace","emoticons":[{"_id":"28087","begin":0,"end":6},{"_id":"28087","begin":8,"end":14},{"_id":"28087","begin":16,"end":22}],"fragments":[{"text":"WutFace","emoticon":{"emoticon_id":"28087","emoticon_set_id":""}},{"text":" "},{"text":"WutFace","emoticon":{"emoticon_id":"28087","emoticon_set_id":""}},{"text":" "},{"text":"WutFace","emoticon":{"emoticon_id":"28087","emoticon_set_id":""}}],"is_action":false,"user_color":"#8A2BE2"},"more_replies":false},{"_id":"dcfa0033-0199-45ef-91a5-afd7c96712c0","created_at":"2019-03-02T20:22:30.529Z","updated_at":"2019-03-02T20:22:30.529Z","channel_id":"23161357","content_type":"video","content_id":"389178879","content_offset_seconds":11887.829,"commenter":{"display_name":"MrLevyBi","_id":"70964298","name":"mrlevybi","type":"user","bio":null,"created_at":"2014-09-10T23:45:07.36423Z","updated_at":"2019-01-15T00:04:02.678225Z","logo":"https://static-cdn.jtvnw.net/jtv_user_pictures/2fd37959-b76a-463c-9536-590d0adc6a65-profile_image-300x300.jpg"},"source":"chat","state":"published","message":{"body":"HYPERJAMMER HYPERJAMMER","fragments":[{"text":"HYPERJAMMER HYPERJAMMER"}],"is_action":false,"user_badges":[{"_id":"subscriber","version":"3"}],"user_color":"#FF0000"},"more_replies":false},{"_id":"6b56245f-23f9-428b-8b05-6745f6d641ae","created_at":"2019-03-02T20:22:30.938Z","updated_at":"2019-03-02T20:22:30.938Z","channel_id":"23161357","content_type":"video","content_id":"389178879","content_offset_seconds":11888.238,"commenter":{"display_name":"MotionMan_","_id":"82904235","name":"motionman_","type":"user","bio":null,"created_at":"2015-02-16T23:55:04.095916Z","updated_at":"2019-01-17T06:22:07.828391Z","logo":"https://static-cdn.jtvnw.net/user-default-pictures/27103734-3cda-44d6-a384-f2ab71e4bb85-profile_image-300x300.jpg"},"source":"chat","state":"published","message":{"body":"FARTS","fragments":[{"text":"FARTS"}],"is_action":false},"more_replies":false},{"_id":"769ee87b-1132-49f5-b4a5-49c6fe49235b","created_at":"2019-03-02T20:22:31.131Z","updated_at":"2019-03-02T20:22:31.131Z","channel_id":"23161357","content_type":"video","content_id":"389178879","content_offset_seconds":11888.431,"commenter":{"display_name":"Gord_the_Rogue","_id":"81628618","name":"gord_the_rogue","type":"user","bio":null,"created_at":"2015-02-02T17:47:37.194793Z","updated_at":"2019-02-26T08:51:24.184418Z","logo":"https://static-cdn.jtvnw.net/jtv_user_pictures/gord_the_rogue-profile_image-595754735bf3bdfb-300x300.jpeg"},"source":"chat","state":"published","message":{"body":"EXPLAIN FLATULENCE","fragments":[{"text":"EXPLAIN FLATULENCE"}],"is_action":false,"user_badges":[{"_id":"subscriber","version":"3"},{"_id":"bits-charity","version":"1"}],"user_color":"#377F95"},"more_replies":false},{"_id":"0ec15eee-2d65-4208-ac5c-bbdaaf857d82","created_at":"2019-03-02T20:22:31.267Z","updated_at":"2019-03-02T20:22:31.267Z","channel_id":"23161357","content_type":"video","content_id":"389178879","content_offset_seconds":11888.567,"commenter":{"display_name":"elsewire","_id":"54217819","name":"elsewire","type":"user","bio":null,"created_at":"2014-01-01T05:11:13.418192Z","updated_at":"2018-09-13T02:57:48.865297Z","logo":"https://static-cdn.jtvnw.net/jtv_user_pictures/elsewire-profile_image-e82061e55b4d8a84-300x300.png"},"source":"chat","state":"published","message":{"body":"it's the short man","fragments":[{"text":"it's the short man"}],"is_action":false,"user_badges":[{"_id":"subscriber","version":"12"},{"_id":"turbo","version":"1"}],"user_color":"#458175"},"more_replies":false},{"_id":"008ae913-b513-4d7e-ac17-0693a253e3a0","created_at":"2019-03-02T20:22:31.938Z","updated_at":"2019-03-02T20:22:31.938Z","channel_id":"23161357","content_type":"video","content_id":"389178879","content_offset_seconds":11889.238,"commenter":{"display_name":"Federock08","_id":"167794765","name":"federock08","type":"user","bio":"Im just a dude who lives in Argentina. Yes, way south america.The #08 its because i used that number when i played basketball. I just like it.","created_at":"2017-08-01T18:21:41.040143Z","updated_at":"2019-03-08T02:06:55.107185Z","logo":"https://static-cdn.jtvnw.net/jtv_user_pictures/7e42f1c4-1988-4162-a2f6-024246a2ce1c-profile_image-300x300.jpg"},"source":"chat","state":"published","message":{"body":"Script Kapp","fragments":[{"text":"Script Kapp"}],"is_action":false,"user_color":"#B22222"},"more_replies":false},{"_id":"462cb390-75e8-4653-b487-94cadca109e4","created_at":"2019-03-02T20:22:33.322Z","updated_at":"2019-03-02T20:22:33.322Z","channel_id":"23161357","content_type":"video","content_id":"389178879","content_offset_seconds":11890.622,"commenter":{"display_name":"Haho_Hahov","_id":"76419558","name":"haho_hahov","type":"user","bio":null,"created_at":"2014-12-02T19:08:05.7835Z","updated_at":"2019-02-16T21:54:59.662668Z","logo":"https://static-cdn.jtvnw.net/jtv_user_pictures/95edf534-5bb6-4429-a655-8077975e134c-profile_image-300x300.png"},"source":"chat","state":"published","message":{"body":"blobD","fragments":[{"text":"blobD"}],"is_action":false,"user_badges":[{"_id":"subscriber","version":"6"}],"user_color":"#DAA520"},"more_replies":false},{"_id":"28d1e68e-d921-4e7e-92e7-3c78d7a26670","created_at":"2019-03-02T20:22:33.606Z","updated_at":"2019-03-02T20:22:33.606Z","channel_id":"23161357","content_type":"video","content_id":"389178879","content_offset_seconds":11890.906,"commenter":{"display_name":"Gamer244543","_id":"91083022","name":"gamer244543","type":"user","bio":null,"created_at":"2015-05-15T04:59:02.404898Z","updated_at":"2019-02-21T11:13:59.82196Z","logo":"https://static-cdn.jtvnw.net/user-default-pictures/49988c7b-57bc-4dee-bd4f-6df4ad215d3a-profile_image-300x300.jpg"},"source":"chat","state":"published","message":{"body":"lirikAYAYA","emoticons":[{"_id":"1498569","begin":0,"end":9}],"fragments":[{"text":"lirikAYAYA","emoticon":{"emoticon_id":"1498569","emoticon_set_id":""}}],"is_action":false,"user_badges":[{"_id":"subscriber","version":"12"},{"_id":"premium","version":"1"}],"user_color":"#0000FF"},"more_replies":false},{"_id":"c9195502-a7ca-4143-b9f6-47c68c70d735","created_at":"2019-03-02T20:22:33.961Z","updated_at":"2019-03-02T20:22:33.961Z","channel_id":"23161357","content_type":"video","content_id":"389178879","content_offset_seconds":11891.261,"commenter":{"display_name":"supremecatt","_id":"128702307","name":"supremecatt","type":"user","bio":null,"created_at":"2016-07-06T00:11:37.476653Z","updated_at":"2019-02-26T17:20:49.681893Z","logo":"https://static-cdn.jtvnw.net/jtv_user_pictures/supremecatt-profile_image-4da28b27207439a1-300x300.jpeg"},"source":"chat","state":"published","message":{"body":"ppJedi pepegaJAMMER ppJedi pepegaJAMMER ppJedi pepegaJAMMER ppJedi pepegaJAMMER ppJedi pepegaJAMMER ppJedi pepegaJAMMER","fragments":[{"text":"ppJedi pepegaJAMMER ppJedi pepegaJAMMER ppJedi pepegaJAMMER ppJedi pepegaJAMMER ppJedi pepegaJAMMER ppJedi pepegaJAMMER"}],"is_action":false,"user_badges":[{"_id":"subscriber","version":"12"}],"user_color":"#1E90FF"},"more_replies":false},{"_id":"f7a43f03-8312-4d70-8db3-da489d0f4856","created_at":"2019-03-02T20:22:35.216Z","updated_at":"2019-03-02T20:22:35.216Z","channel_id":"23161357","content_type":"video","content_id":"389178879","content_offset_seconds":11892.516,"commenter":{"display_name":"cinzan","_id":"47455956","name":"cinzan","type":"user","bio":null,"created_at":"2013-08-11T20:49:15.266919Z","updated_at":"2019-02-27T19:11:06.642478Z","logo":"https://static-cdn.jtvnw.net/user-default-pictures/49988c7b-57bc-4dee-bd4f-6df4ad215d3a-profile_image-300x300.jpg"},"source":"chat","state":"published","message":{"body":"you probably killed someone with that","fragments":[{"text":"you probably killed someone with that"}],"is_action":false,"user_badges":[{"_id":"subscriber","version":"24"}],"user_color":"#D2691E"},"more_replies":false},{"_id":"d01d29e1-6fc7-4033-ac64-59eed41d336e","created_at":"2019-03-02T20:22:35.825Z","updated_at":"2019-03-02T20:22:35.825Z","channel_id":"23161357","content_type":"video","content_id":"389178879","content_offset_seconds":11893.125,"commenter":{"display_name":"National89","_id":"27591102","name":"national89","type":"user","bio":"there is always a choice","created_at":"2012-01-20T03:09:51.213791Z","updated_at":"2019-02-16T15:30:59.203765Z","logo":"https://static-cdn.jtvnw.net/jtv_user_pictures/9871f821-ba2f-43e8-af77-cab5a3446cc3-profile_image-300x300.jpg"},"source":"chat","state":"published","message":{"body":"HYPERJAMMER pepegaJAMMER HYPERJAMMER","fragments":[{"text":"HYPERJAMMER pepegaJAMMER HYPERJAMMER"}],"is_action":false,"user_badges":[{"_id":"subscriber","version":"24"},{"_id":"turbo","version":"1"}],"user_color":"#A9BFFF"},"more_replies":false},{"_id":"5e6d529d-5c6a-4f44-b9f3-a468583b6dc2","created_at":"2019-03-02T20:22:37.082Z","updated_at":"2019-03-02T20:22:37.082Z","channel_id":"23161357","content_type":"video","content_id":"389178879","content_offset_seconds":11894.382,"commenter":{"display_name":"LiIyana","_id":"166741120","name":"liiyana","type":"user","bio":null,"created_at":"2017-07-26T07:13:16.423038Z","updated_at":"2019-03-10T11:03:59.93738Z","logo":"https://static-cdn.jtvnw.net/jtv_user_pictures/d8984ac2-ba68-4b1a-aab7-efdd95674a27-profile_image-300x300.jpg"},"source":"chat","state":"published","message":{"body":"hi","fragments":[{"text":"hi"}],"is_action":false,"user_badges":[{"_id":"turbo","version":"1"}],"user_color":"#81EFFC"},"more_replies":false},{"_id":"a32bae94-f866-4f40-9f0e-cf4393ed5515","created_at":"2019-03-02T20:22:37.233Z","updated_at":"2019-03-02T20:22:37.233Z","channel_id":"23161357","content_type":"video","content_id":"389178879","content_offset_seconds":11894.533,"commenter":{"display_name":"Melati1","_id":"70435519","name":"melati1","type":"user","bio":null,"created_at":"2014-09-01T21:46:21.860537Z","updated_at":"2019-03-09T08:46:38.780532Z","logo":"https://static-cdn.jtvnw.net/jtv_user_pictures/melati1-profile_image-34ddd92f8e4f3863-300x300.jpeg"},"source":"chat","state":"published","message":{"body":"TableHere TableHere TableHere","emoticons":[{"_id":"115845","begin":0,"end":8},{"_id":"115845","begin":10,"end":18},{"_id":"115845","begin":20,"end":28}],"fragments":[{"text":"TableHere","emoticon":{"emoticon_id":"115845","emoticon_set_id":""}},{"text":" "},{"text":"TableHere","emoticon":{"emoticon_id":"115845","emoticon_set_id":""}},{"text":" "},{"text":"TableHere","emoticon":{"emoticon_id":"115845","emoticon_set_id":""}}],"is_action":false,"user_badges":[{"_id":"subscriber","version":"0"},{"_id":"premium","version":"1"}],"user_color":"#B10505"},"more_replies":false},{"_id":"709db237-75c8-4b9b-8925-e8b98e9073cd","created_at":"2019-03-02T20:22:37.986Z","updated_at":"2019-03-02T20:22:37.986Z","channel_id":"23161357","content_type":"video","content_id":"389178879","content_offset_seconds":11895.286,"commenter":{"display_name":"TheScentofaMan","_id":"98244589","name":"thescentofaman","type":"user","bio":null,"created_at":"2015-08-04T18:48:29.293722Z","updated_at":"2019-02-25T21:32:09.362039Z","logo":"https://static-cdn.jtvnw.net/jtv_user_pictures/c2c5ae17-157f-428a-839d-971048aa605c-profile_image-300x300.jpg"},"source":"chat","state":"published","message":{"body":"@lirik we heard a fart asmr","fragments":[{"text":"@lirik we heard a fart asmr"}],"is_action":false,"user_badges":[{"_id":"subscriber","version":"24"}],"user_color":"#FFE0A3"},"more_replies":false},{"_id":"d90b5259-2e1f-400e-a218-8d0a7deda6fe","created_at":"2019-03-02T20:22:38.044Z","updated_at":"2019-03-02T20:22:38.044Z","channel_id":"23161357","content_type":"video","content_id":"389178879","content_offset_seconds":11895.344,"commenter":{"display_name":"bl00dline954","_id":"58637256","name":"bl00dline954","type":"user","bio":"100 Mile Finisher! Student At Broward College. AMP Human Performance, BeardedOwl, Nuun Hydration And Pro-Tec Athletics Ambassador. Runner's Depot Racing Team.","created_at":"2014-03-11T17:20:13.705785Z","updated_at":"2019-03-08T23:02:07.582221Z","logo":"https://static-cdn.jtvnw.net/jtv_user_pictures/da701ca6-1790-4ec8-8918-30302bb5ada5-profile_image-300x300.jpeg"},"source":"chat","state":"published","message":{"body":"shor t guyyyyy\\","fragments":[{"text":"shor t guyyyyy\\"}],"is_action":false,"user_badges":[{"_id":"subscriber","version":"6"},{"_id":"premium","version":"1"}]},"more_replies":false},{"_id":"0b2625e2-1b2b-489b-8b7f-2d6fe4b055fe","created_at":"2019-03-02T20:22:38.05Z","updated_at":"2019-03-02T20:22:38.05Z","channel_id":"23161357","content_type":"video","content_id":"389178879","content_offset_seconds":11895.35,"commenter":{"display_name":"ayrancoia","_id":"209095294","name":"ayrancoia","type":"user","bio":"I´m not relefant.","created_at":"2018-03-27T17:29:12.341382Z","updated_at":"2019-03-06T22:28:01.599687Z","logo":"https://static-cdn.jtvnw.net/jtv_user_pictures/65a27414-7d02-4cfc-878d-7c5faf136ce5-profile_image-300x300.jpeg"},"source":"chat","state":"published","message":{"body":"blobD","fragments":[{"text":"blobD"}],"is_action":false,"user_badges":[{"_id":"subscriber","version":"6"}],"user_color":"#8A2BE2"},"more_replies":false},{"_id":"5ed7c54f-6b54-460f-9299-94a04f84431f","created_at":"2019-03-02T20:22:38.235Z","updated_at":"2019-03-02T20:22:38.235Z","channel_id":"23161357","content_type":"video","content_id":"389178879","content_offset_seconds":11895.535,"commenter":{"display_name":"MarkZS20","_id":"91030985","name":"markzs20","type":"user","bio":null,"created_at":"2015-05-14T15:04:30.285827Z","updated_at":"2019-03-06T22:25:24.165265Z","logo":"https://static-cdn.jtvnw.net/jtv_user_pictures/ee19d51e-794a-4e44-87b6-6365d1bcd83f-profile_image-300x300.png"},"source":"chat","state":"published","message":{"body":"Pog ostuck","fragments":[{"text":"Pog ostuck"}],"is_action":false,"user_color":"#DAA520"},"more_replies":false},{"_id":"85577e25-cd19-41a1-ae4a-0e57ab14b6d2","created_at":"2019-03-02T20:22:38.56Z","updated_at":"2019-03-02T20:22:38.56Z","channel_id":"23161357","content_type":"video","content_id":"389178879","content_offset_seconds":11895.86,"commenter":{"display_name":"MvPGEO","_id":"29546842","name":"mvpgeo","type":"user","bio":"Chilling stream, playing mobile game! PUBG Mobile, Onmyoji Arena, Heroes Arena, Vainglory etc. I love good music and good games. Come join me and hope you will have fun watching me playing :)Follow me on Twitter @MvPGEO89 Keep it cool! Poggers","created_at":"2012-04-06T09:04:28.693182Z","updated_at":"2019-03-01T14:19:59.838402Z","logo":"https://static-cdn.jtvnw.net/jtv_user_pictures/19f2b3a8-a3d2-4b18-80f1-d9cd85cc8264-profile_image-300x300.jpg"},"source":"chat","state":"published","message":{"body":"Pogo cuck OMEGALUL","fragments":[{"text":"Pogo cuck OMEGALUL"}],"is_action":false,"user_badges":[{"_id":"subscriber","version":"6"},{"_id":"premium","version":"1"}],"user_color":"#FDF800"},"more_replies":false},{"_id":"06ba1d2e-6589-45b3-ab57-4eeb5a4ee373","created_at":"2019-03-02T20:22:39.065Z","updated_at":"2019-03-02T20:22:39.065Z","channel_id":"23161357","content_type":"video","content_id":"389178879","content_offset_seconds":11896.365,"commenter":{"display_name":"ApexCryptLord","_id":"74479085","name":"apexcryptlord","type":"user","bio":"https://twitter.com/AkatzukiLeadeRhttps://apexcryptlord.deviantart.com/","created_at":"2014-11-04T17:56:55.675801Z","updated_at":"2019-03-06T14:51:38.988142Z","logo":"https://static-cdn.jtvnw.net/jtv_user_pictures/f99b66fa-bd53-43bb-a37c-f3eb2b735869-profile_image-300x300.png"},"source":"chat","state":"published","message":{"body":"https://clips.twitch.tv/BoldObliviousLadiesBlargNaut","fragments":[{"text":"https://clips.twitch.tv/BoldObliviousLadiesBlargNaut"}],"is_action":false,"user_badges":[{"_id":"subscriber","version":"24"},{"_id":"premium","version":"1"}],"user_color":"#9C00CC"},"more_replies":false},{"_id":"78026b11-82f1-4751-968d-6ccab276a301","created_at":"2019-03-02T20:22:39.898Z","updated_at":"2019-03-02T20:22:39.898Z","channel_id":"23161357","content_type":"video","content_id":"389178879","content_offset_seconds":11897.198,"commenter":{"display_name":"LiveNOW_TV","_id":"90867896","name":"livenow_tv","type":"user","bio":"...stay tuned for further informations","created_at":"2015-05-12T04:55:29.12331Z","updated_at":"2019-03-04T09:49:12.361502Z","logo":"https://static-cdn.jtvnw.net/jtv_user_pictures/livenow_tv-profile_image-9da4edd0088d1127-300x300.jpeg"},"source":"chat","state":"published","message":{"body":"4 Tetris WINS?!?! PogChamp","emoticons":[{"_id":"88","begin":18,"end":25}],"fragments":[{"text":"4 Tetris WINS?!?! "},{"text":"PogChamp","emoticon":{"emoticon_id":"88","emoticon_set_id":""}}],"is_action":false,"user_color":"#008000"},"more_replies":false},{"_id":"0ab25e43-4773-40bc-a173-dd2d92b054d7","created_at":"2019-03-02T20:22:42.489Z","updated_at":"2019-03-02T20:22:42.489Z","channel_id":"23161357","content_type":"video","content_id":"389178879","content_offset_seconds":11899.789,"commenter":{"display_name":"dominus1972","_id":"130926887","name":"dominus1972","type":"user","bio":null,"created_at":"2016-07-31T01:17:28.879007Z","updated_at":"2019-03-04T16:34:37.705482Z","logo":"https://static-cdn.jtvnw.net/user-default-pictures/bb97f7e6-f11a-4194-9708-52bf5a5125e8-profile_image-300x300.jpg"},"source":"chat","state":"published","message":{"body":"Pog O","fragments":[{"text":"Pog O"}],"is_action":false,"user_badges":[{"_id":"subscriber","version":"0"}]},"more_replies":false},{"_id":"238121e2-05aa-44f7-aa99-589b09318d84","created_at":"2019-03-02T20:22:42.848Z","updated_at":"2019-03-02T20:22:42.848Z","channel_id":"23161357","content_type":"video","content_id":"389178879","content_offset_seconds":11900.148,"commenter":{"display_name":"tempobrian","_id":"51846711","name":"tempobrian","type":"user","bio":null,"created_at":"2013-11-20T02:32:53.262207Z","updated_at":"2019-03-05T06:51:27.519333Z","logo":"https://static-cdn.jtvnw.net/jtv_user_pictures/tempobrian-profile_image-dda56e3eebd38a3b-300x300.png"},"source":"chat","state":"published","message":{"body":"DMs lirikLEWD","emoticons":[{"_id":"1771988","begin":4,"end":12}],"fragments":[{"text":"DMs "},{"text":"lirikLEWD","emoticon":{"emoticon_id":"1771988","emoticon_set_id":""}}],"is_action":false,"user_badges":[{"_id":"subscriber","version":"36"},{"_id":"bits","version":"10000"}],"user_color":"#9CF9F9"},"more_replies":false},{"_id":"8eab0540-5193-4c17-973c-a058fd33ee1d","created_at":"2019-03-02T20:22:43.809Z","updated_at":"2019-03-02T20:22:43.809Z","channel_id":"23161357","content_type":"video","content_id":"389178879","content_offset_seconds":11901.109,"commenter":{"display_name":"CudyPew","_id":"44063327","name":"cudypew","type":"user","bio":null,"created_at":"2013-05-28T15:34:50.637021Z","updated_at":"2019-01-23T16:59:53.797542Z","logo":"https://static-cdn.jtvnw.net/user-default-pictures/bb97f7e6-f11a-4194-9708-52bf5a5125e8-profile_image-300x300.jpg"},"source":"chat","state":"published","message":{"body":"game is a bit loud","fragments":[{"text":"game is a bit loud"}],"is_action":false,"user_color":"#FF0000"},"more_replies":false},{"_id":"37857434-3137-435b-b8b1-3bd4bd81bbfe","created_at":"2019-03-02T20:22:46.648Z","updated_at":"2019-03-02T20:22:46.648Z","channel_id":"23161357","content_type":"video","content_id":"389178879","content_offset_seconds":11903.948,"commenter":{"display_name":"Voic","_id":"135074091","name":"voic","type":"user","bio":null,"created_at":"2016-09-20T15:10:14.305983Z","updated_at":"2019-02-21T01:18:23.419054Z","logo":"https://static-cdn.jtvnw.net/jtv_user_pictures/cb8c7ef1-dbdd-4d8b-94d0-8a171e527302-profile_image-300x300.jpg"},"source":"chat","state":"published","message":{"body":"Mute didnt work when you farted Lirik","fragments":[{"text":"Mute didnt work when you farted Lirik"}],"is_action":false,"user_color":"#9ACD32"},"more_replies":false},{"_id":"b599f3f9-b1c4-450a-bb4a-8382600a2f51","created_at":"2019-03-02T20:22:46.829Z","updated_at":"2019-03-02T20:22:46.829Z","channel_id":"23161357","content_type":"video","content_id":"389178879","content_offset_seconds":11904.129,"commenter":{"display_name":"Fossabot","_id":"237719657","name":"fossabot","type":"user","bio":"Twitch moderation bot","created_at":"2018-07-10T20:56:46.030491Z","updated_at":"2019-03-10T09:42:23.069413Z","logo":"https://static-cdn.jtvnw.net/jtv_user_pictures/0b2418e6-aa1e-45f4-b974-73acc78f8cd4-profile_image-300x300.png"},"source":"chat","state":"published","message":{"body":"NightMethod with Twitch Prime sub! lirikH","emoticons":[{"_id":"1498561","begin":35,"end":40}],"fragments":[{"text":"NightMethod with Twitch Prime sub! "},{"text":"lirikH","emoticon":{"emoticon_id":"1498561","emoticon_set_id":""}}],"is_action":false,"user_badges":[{"_id":"moderator","version":"1"},{"_id":"subscriber","version":"3"}],"user_color":"#3F51B5"},"more_replies":false},{"_id":"0d601b25-5480-410c-b67e-1eab40214bfb","created_at":"2019-03-02T20:22:47.541Z","updated_at":"2019-03-02T20:22:47.541Z","channel_id":"23161357","content_type":"video","content_id":"389178879","content_offset_seconds":11904.841,"commenter":{"display_name":"Datpokeguy","_id":"57377650","name":"datpokeguy","type":"user","bio":null,"created_at":"2014-02-21T21:51:56.620795Z","updated_at":"2019-03-09T20:45:25.429366Z","logo":"https://static-cdn.jtvnw.net/jtv_user_pictures/datpokeguy-profile_image-51687bdc3a19c854-300x300.jpeg"},"source":"chat","state":"published","message":{"body":"Late night DMs lirikLEWD lirikLEWD lirikLEWD","emoticons":[{"_id":"1771988","begin":15,"end":23},{"_id":"1771988","begin":25,"end":33},{"_id":"1771988","begin":35,"end":43}],"fragments":[{"text":"Late night DMs "},{"text":"lirikLEWD","emoticon":{"emoticon_id":"1771988","emoticon_set_id":""}},{"text":" "},{"text":"lirikLEWD","emoticon":{"emoticon_id":"1771988","emoticon_set_id":""}},{"text":" "},{"text":"lirikLEWD","emoticon":{"emoticon_id":"1771988","emoticon_set_id":""}}],"is_action":false,"user_badges":[{"_id":"subscriber","version":"0"}],"user_color":"#0000FF"},"more_replies":false},{"_id":"92e7f123-bee7-480e-9ea7-d73b25f7b714","created_at":"2019-03-02T20:22:47.91Z","updated_at":"2019-03-02T20:22:47.91Z","channel_id":"23161357","content_type":"video","content_id":"389178879","content_offset_seconds":11905.21,"commenter":{"display_name":"Angeroth","_id":"66889618","name":"angeroth","type":"user","bio":null,"created_at":"2014-07-21T17:31:06.940252Z","updated_at":"2019-03-09T23:42:51.891099Z","logo":"https://static-cdn.jtvnw.net/jtv_user_pictures/angeroth-profile_image-742e5a149f9e441b-300x300.jpeg"},"source":"chat","state":"published","message":{"body":"u can POGO my STICK m0xyHand1 m0xyEZ m0xyHand2","emoticons":[{"_id":"1413343","begin":20,"end":28},{"_id":"1413309","begin":30,"end":35},{"_id":"1413346","begin":37,"end":45}],"fragments":[{"text":"u can POGO my STICK "},{"text":"m0xyHand1","emoticon":{"emoticon_id":"1413343","emoticon_set_id":""}},{"text":" "},{"text":"m0xyEZ","emoticon":{"emoticon_id":"1413309","emoticon_set_id":""}},{"text":" "},{"text":"m0xyHand2","emoticon":{"emoticon_id":"1413346","emoticon_set_id":""}}],"is_action":false,"user_badges":[{"_id":"subscriber","version":"48"}],"user_color":"#FF0000"},"more_replies":false},{"_id":"e93b663d-2b1b-4fd8-bc5c-6bbf0fc9d1b5","created_at":"2019-03-02T20:22:48.295Z","updated_at":"2019-03-02T20:22:48.295Z","channel_id":"23161357","content_type":"video","content_id":"389178879","content_offset_seconds":11905.595,"commenter":{"display_name":"MotionMan_","_id":"82904235","name":"motionman_","type":"user","bio":null,"created_at":"2015-02-16T23:55:04.095916Z","updated_at":"2019-01-17T06:22:07.828391Z","logo":"https://static-cdn.jtvnw.net/user-default-pictures/27103734-3cda-44d6-a384-f2ab71e4bb85-profile_image-300x300.jpg"},"source":"chat","state":"published","message":{"body":"Clip ?","fragments":[{"text":"Clip ?"}],"is_action":false},"more_replies":false},{"_id":"fdcf32c1-1a05-4000-b083-ab21ef7efa8b","created_at":"2019-03-02T20:22:48.592Z","updated_at":"2019-03-02T20:22:48.592Z","channel_id":"23161357","content_type":"video","content_id":"389178879","content_offset_seconds":11905.892,"commenter":{"display_name":"MeemphysS","_id":"28469020","name":"meemphyss","type":"user","bio":null,"created_at":"2012-02-24T17:47:42.734658Z","updated_at":"2019-03-09T16:34:31.667628Z","logo":"https://static-cdn.jtvnw.net/user-default-pictures/b83b1794-7df9-4878-916c-88c2ad2e4f9f-profile_image-300x300.jpg"},"source":"chat","state":"published","message":{"body":"nice clips chimps WeirdChamp","fragments":[{"text":"nice clips chimps WeirdChamp"}],"is_action":false,"user_color":"#B139B1"},"more_replies":false},{"_id":"a8cb2f1b-b945-4cb6-a1ac-2d63dfc0210b","created_at":"2019-03-02T20:22:49.858Z","updated_at":"2019-03-02T20:22:49.858Z","channel_id":"23161357","content_type":"video","content_id":"389178879","content_offset_seconds":11907.158,"commenter":{"display_name":"ayrancoia","_id":"209095294","name":"ayrancoia","type":"user","bio":"I´m not relefant.","created_at":"2018-03-27T17:29:12.341382Z","updated_at":"2019-03-06T22:28:01.599687Z","logo":"https://static-cdn.jtvnw.net/jtv_user_pictures/65a27414-7d02-4cfc-878d-7c5faf136ce5-profile_image-300x300.jpeg"},"source":"chat","state":"published","message":{"body":"Kapp","fragments":[{"text":"Kapp"}],"is_action":false,"user_badges":[{"_id":"subscriber","version":"6"}],"user_color":"#8A2BE2"},"more_replies":false},{"_id":"13b59b45-0bbe-400f-924e-de51bcc8cb44","created_at":"2019-03-02T20:22:49.88Z","updated_at":"2019-03-02T20:22:49.88Z","channel_id":"23161357","content_type":"video","content_id":"389178879","content_offset_seconds":11907.18,"commenter":{"display_name":"AnarchistQ","_id":"30583163","name":"anarchistq","type":"user","bio":"I keep 2 myself...","created_at":"2012-05-16T17:41:50.107042Z","updated_at":"2019-03-08T01:54:41.921543Z","logo":"https://static-cdn.jtvnw.net/jtv_user_pictures/anarchistq-profile_image-db15387f89271d29-300x300.jpeg"},"source":"chat","state":"published","message":{"body":"sure","fragments":[{"text":"sure"}],"is_action":false,"user_badges":[{"_id":"subscriber","version":"12"},{"_id":"bits","version":"5000"}],"user_color":"#000038"},"more_replies":false},{"_id":"7b50fd26-2d64-46f4-9d56-756605e75a51","created_at":"2019-03-02T20:22:50.2Z","updated_at":"2019-03-02T20:22:50.2Z","channel_id":"23161357","content_type":"video","content_id":"389178879","content_offset_seconds":11907.5,"commenter":{"display_name":"feedmesomewaaagh___","_id":"118335180","name":"feedmesomewaaagh___","type":"user","bio":null,"created_at":"2016-03-10T14:39:15.134946Z","updated_at":"2018-12-17T04:28:10.585022Z","logo":"https://static-cdn.jtvnw.net/user-default-pictures/4cbf10f1-bb9f-4f57-90e1-15bf06cfe6f5-profile_image-300x300.jpg"},"source":"chat","state":"published","message":{"body":"Tetris PJSalt 99","emoticons":[{"_id":"36","begin":7,"end":12}],"fragments":[{"text":"Tetris "},{"text":"PJSalt","emoticon":{"emoticon_id":"36","emoticon_set_id":""}},{"text":" 99"}],"is_action":false},"more_replies":false},{"_id":"370a102f-25a5-4068-a740-11f4e092fe0b","created_at":"2019-03-02T20:22:50.762Z","updated_at":"2019-03-02T20:22:50.762Z","channel_id":"23161357","content_type":"video","content_id":"389178879","content_offset_seconds":11908.062,"commenter":{"display_name":"talo7","_id":"43791712","name":"talo7","type":"user","bio":"(ツ)","created_at":"2013-05-21T05:11:12.298631Z","updated_at":"2019-03-05T04:04:10.864522Z","logo":"https://static-cdn.jtvnw.net/jtv_user_pictures/ad5f1eba-3cc2-48dd-b3e1-0d172b945cd6-profile_image-300x300.png"},"source":"chat","state":"published","message":{"body":"Kapp","fragments":[{"text":"Kapp"}],"is_action":false,"user_badges":[{"_id":"premium","version":"1"}],"user_color":"#FF5200"},"more_replies":false},{"_id":"1a4102a9-1287-4fb3-9c3f-b423e0254cac","created_at":"2019-03-02T20:22:50.783Z","updated_at":"2019-03-02T20:22:50.783Z","channel_id":"23161357","content_type":"video","content_id":"389178879","content_offset_seconds":11908.083,"commenter":{"display_name":"Hectic001","_id":"140876678","name":"hectic001","type":"user","bio":null,"created_at":"2016-12-02T10:50:58.654972Z","updated_at":"2018-12-02T13:50:47.34408Z","logo":"https://static-cdn.jtvnw.net/user-default-pictures/27103734-3cda-44d6-a384-f2ab71e4bb85-profile_image-300x300.jpg"},"source":"chat","state":"published","message":{"body":"@LIRIK Project Winter? PogChamp","emoticons":[{"_id":"88","begin":23,"end":30}],"fragments":[{"text":"@LIRIK Project Winter? "},{"text":"PogChamp","emoticon":{"emoticon_id":"88","emoticon_set_id":""}}],"is_action":false,"user_color":"#1E90FF"},"more_replies":false},{"_id":"72cc1998-c64d-4683-a2e2-6a27b758001c","created_at":"2019-03-02T20:22:51.119Z","updated_at":"2019-03-02T20:22:51.119Z","channel_id":"23161357","content_type":"video","content_id":"389178879","content_offset_seconds":11908.419,"commenter":{"display_name":"MvPGEO","_id":"29546842","name":"mvpgeo","type":"user","bio":"Chilling stream, playing mobile game! PUBG Mobile, Onmyoji Arena, Heroes Arena, Vainglory etc. I love good music and good games. Come join me and hope you will have fun watching me playing :)Follow me on Twitter @MvPGEO89 Keep it cool! Poggers","created_at":"2012-04-06T09:04:28.693182Z","updated_at":"2019-03-01T14:19:59.838402Z","logo":"https://static-cdn.jtvnw.net/jtv_user_pictures/19f2b3a8-a3d2-4b18-80f1-d9cd85cc8264-profile_image-300x300.jpg"},"source":"chat","state":"published","message":{"body":"sure Kappa","emoticons":[{"_id":"25","begin":5,"end":9}],"fragments":[{"text":"sure "},{"text":"Kappa","emoticon":{"emoticon_id":"25","emoticon_set_id":""}}],"is_action":false,"user_badges":[{"_id":"subscriber","version":"6"},{"_id":"premium","version":"1"}],"user_color":"#FDF800"},"more_replies":false},{"_id":"109223c6-84c7-45c0-90b6-e6a68e0bf468","created_at":"2019-03-02T20:22:51.247Z","updated_at":"2019-03-02T20:22:51.247Z","channel_id":"23161357","content_type":"video","content_id":"389178879","content_offset_seconds":11908.547,"commenter":{"display_name":"NotLeeroy","_id":"59810600","name":"notleeroy","type":"user","bio":"Professional lizard, Baguette-fu Sensei and global elite salt miner","created_at":"2014-03-29T00:43:13.594579Z","updated_at":"2018-12-20T21:45:57.950453Z","logo":"https://static-cdn.jtvnw.net/jtv_user_pictures/notleeroy-profile_image-678e08b4da9d4e24-300x300.png"},"source":"chat","state":"published","message":{"body":"doing great angeroth bb","fragments":[{"text":"doing great angeroth bb"}],"is_action":false,"user_color":"#0000FF"},"more_replies":false},{"_id":"e4b86d37-1368-4226-8c04-dbe49dbc6608","created_at":"2019-03-02T20:22:51.41Z","updated_at":"2019-03-02T20:22:51.41Z","channel_id":"23161357","content_type":"video","content_id":"389178879","content_offset_seconds":11908.71,"commenter":{"display_name":"The_Friday_13","_id":"91060818","name":"the_friday_13","type":"user","bio":null,"created_at":"2015-05-14T21:36:37.952227Z","updated_at":"2019-03-06T09:39:42.788225Z","logo":"https://static-cdn.jtvnw.net/jtv_user_pictures/9f0b3aae-1c87-450d-aa70-4f6ccf2cd975-profile_image-300x300.png"},"source":"chat","state":"published","message":{"body":"lirikLUL","emoticons":[{"_id":"1771975","begin":0,"end":7}],"fragments":[{"text":"lirikLUL","emoticon":{"emoticon_id":"1771975","emoticon_set_id":""}}],"is_action":false,"user_badges":[{"_id":"subscriber","version":"12"}],"user_color":"#00B4CC"},"more_replies":false},{"_id":"a2e7a948-93bb-4629-9667-51e47920c762","created_at":"2019-03-02T20:22:51.838Z","updated_at":"2019-03-02T20:22:51.838Z","channel_id":"23161357","content_type":"video","content_id":"389178879","content_offset_seconds":11909.138,"commenter":{"display_name":"Krakarjack","_id":"76226091","name":"krakarjack","type":"user","bio":null,"created_at":"2014-11-29T22:09:34.893922Z","updated_at":"2019-02-23T20:26:22.447002Z","logo":"https://static-cdn.jtvnw.net/user-default-pictures/cd618d3e-f14d-4960-b7cf-094231b04735-profile_image-300x300.jpg"},"source":"chat","state":"published","message":{"body":"Kapp","fragments":[{"text":"Kapp"}],"is_action":false,"user_badges":[{"_id":"subscriber","version":"12"}],"user_color":"#09B3A8"},"more_replies":false},{"_id":"12f0582e-a728-413b-a8bc-7762b1f680a2","created_at":"2019-03-02T20:22:51.854Z","updated_at":"2019-03-02T20:22:51.854Z","channel_id":"23161357","content_type":"video","content_id":"389178879","content_offset_seconds":11909.154,"commenter":{"display_name":"Playd","_id":"103606347","name":"playd","type":"user","bio":null,"created_at":"2015-10-03T19:48:23.267983Z","updated_at":"2019-03-01T05:19:20.547297Z","logo":"https://static-cdn.jtvnw.net/jtv_user_pictures/f8a48a1d-548b-4883-9ba6-24245bee6151-profile_image-300x300.png"},"source":"chat","state":"published","message":{"body":"Kapp","fragments":[{"text":"Kapp"}],"is_action":false,"user_badges":[{"_id":"subscriber","version":"0"},{"_id":"bits-charity","version":"1"}],"user_color":"#00CCBE"},"more_replies":false},{"_id":"fa9e80d3-fb01-4564-9ba7-575d79b6d9bc","created_at":"2019-03-02T20:22:51.936Z","updated_at":"2019-03-02T20:22:51.936Z","channel_id":"23161357","content_type":"video","content_id":"389178879","content_offset_seconds":11909.236,"commenter":{"display_name":"Hunter99RFC","_id":"60855963","name":"hunter99rfc","type":"user","bio":"Glasgow Rangers Football Club, Love RPGs and Action games","created_at":"2014-04-14T16:33:27.815915Z","updated_at":"2019-01-31T18:57:04.632666Z","logo":"https://static-cdn.jtvnw.net/jtv_user_pictures/88c0c50a-6527-43a8-a93c-01232cc9de41-profile_image-300x300.jpg"},"source":"chat","state":"published","message":{"body":"Kapp","fragments":[{"text":"Kapp"}],"is_action":false,"user_badges":[{"_id":"subscriber","version":"24"},{"_id":"premium","version":"1"}],"user_color":"#FF0000"},"more_replies":false},{"_id":"762ca6bb-748d-455b-8ed6-76d926feec32","created_at":"2019-03-02T20:22:52.218Z","updated_at":"2019-03-02T20:22:52.218Z","channel_id":"23161357","content_type":"video","content_id":"389178879","content_offset_seconds":11909.518,"commenter":{"display_name":"eWaaGe","_id":"26080350","name":"ewaage","type":"user","bio":"Welcome to my stream :)","created_at":"2011-11-12T12:44:30.84829Z","updated_at":"2019-02-28T22:46:50.264365Z","logo":"https://static-cdn.jtvnw.net/jtv_user_pictures/f73c349b-9aa1-467d-93ff-17231e79095d-profile_image-300x300.png"},"source":"chat","state":"published","message":{"body":"pepegaJAMMER","fragments":[{"text":"pepegaJAMMER"}],"is_action":false,"user_badges":[{"_id":"subscriber","version":"12"}],"user_color":"#FF69B4"},"more_replies":false},{"_id":"0456fa5f-688c-4374-a073-ecf5fba069c9","created_at":"2019-03-02T20:22:52.295Z","updated_at":"2019-03-02T20:22:52.295Z","channel_id":"23161357","content_type":"video","content_id":"389178879","content_offset_seconds":11909.595,"commenter":{"display_name":"beardTHEbear","_id":"77548071","name":"beardthebear","type":"user","bio":null,"created_at":"2014-12-20T03:25:55.077099Z","updated_at":"2019-03-10T00:30:15.241866Z","logo":"https://static-cdn.jtvnw.net/jtv_user_pictures/beardthebear-profile_image-e18114afc029a3af-300x300.png"},"source":"chat","state":"published","message":{"body":"sure Kapp","fragments":[{"text":"sure Kapp"}],"is_action":false,"user_badges":[{"_id":"bits-charity","version":"1"}],"user_color":"#00CCCC"},"more_replies":false},{"_id":"43a8962b-ac65-491d-a1ec-d1d877c35099","created_at":"2019-03-02T20:22:52.445Z","updated_at":"2019-03-02T20:22:52.445Z","channel_id":"23161357","content_type":"video","content_id":"389178879","content_offset_seconds":11909.745,"commenter":{"display_name":"KCthree","_id":"37552978","name":"kcthree","type":"user","bio":null,"created_at":"2012-11-09T18:11:33.060849Z","updated_at":"2019-03-10T00:55:47.562312Z","logo":"https://static-cdn.jtvnw.net/jtv_user_pictures/kcthree-profile_image-7f906fdc6fbe0f0c-300x300.jpeg"},"source":"chat","state":"published","message":{"body":"@SurfMako lirikA","emoticons":[{"_id":"1795151","begin":10,"end":15}],"fragments":[{"text":"@SurfMako "},{"text":"lirikA","emoticon":{"emoticon_id":"1795151","emoticon_set_id":""}}],"is_action":false,"user_badges":[{"_id":"subscriber","version":"12"}],"user_color":"#CC6900"},"more_replies":false},{"_id":"a026d35f-8c38-41d8-8a70-f761fc933fc6","created_at":"2019-03-02T20:22:53.574Z","updated_at":"2019-03-02T20:22:53.574Z","channel_id":"23161357","content_type":"video","content_id":"389178879","content_offset_seconds":11910.874,"commenter":{"display_name":"MarkZS20","_id":"91030985","name":"markzs20","type":"user","bio":null,"created_at":"2015-05-14T15:04:30.285827Z","updated_at":"2019-03-06T22:25:24.165265Z","logo":"https://static-cdn.jtvnw.net/jtv_user_pictures/ee19d51e-794a-4e44-87b6-6365d1bcd83f-profile_image-300x300.png"},"source":"chat","state":"published","message":{"body":"Kapp","fragments":[{"text":"Kapp"}],"is_action":false,"user_color":"#DAA520"},"more_replies":false},{"_id":"f1973965-fdd0-4d67-9a09-8df076e832bb","created_at":"2019-03-02T20:22:53.993Z","updated_at":"2019-03-02T20:22:53.993Z","channel_id":"23161357","content_type":"video","content_id":"389178879","content_offset_seconds":11911.293,"commenter":{"display_name":"BlackM13","_id":"73183768","name":"blackm13","type":"user","bio":"Mazel Tov","created_at":"2014-10-16T21:10:23.739247Z","updated_at":"2019-01-01T18:05:33.343273Z","logo":"https://static-cdn.jtvnw.net/user-default-pictures/bb97f7e6-f11a-4194-9708-52bf5a5125e8-profile_image-300x300.jpg"},"source":"chat","state":"published","message":{"body":"stuck Pog ?","fragments":[{"text":"stuck Pog ?"}],"is_action":false,"user_color":"#1E90FF"},"more_replies":false},{"_id":"a9f05ed0-cf0d-4186-ba7b-8181492a2d35","created_at":"2019-03-02T20:22:54.519Z","updated_at":"2019-03-02T20:22:54.519Z","channel_id":"23161357","content_type":"video","content_id":"389178879","content_offset_seconds":11911.819,"commenter":{"display_name":"katimirputin","_id":"98709863","name":"katimirputin","type":"user","bio":null,"created_at":"2015-08-09T09:10:04.363274Z","updated_at":"2019-03-10T12:55:30.163317Z","logo":"https://static-cdn.jtvnw.net/user-default-pictures/bb97f7e6-f11a-4194-9708-52bf5a5125e8-profile_image-300x300.jpg"},"source":"chat","state":"published","message":{"body":"Kappa sure","emoticons":[{"_id":"25","begin":0,"end":4}],"fragments":[{"text":"Kappa","emoticon":{"emoticon_id":"25","emoticon_set_id":""}},{"text":" sure"}],"is_action":false,"user_badges":[{"_id":"subscriber","version":"12"},{"_id":"bits","version":"1000"}],"user_color":"#19B3AB"},"more_replies":false},{"_id":"9d5064d7-8777-481a-ad1c-a9a55163e38d","created_at":"2019-03-02T20:22:54.698Z","updated_at":"2019-03-02T20:22:54.698Z","channel_id":"23161357","content_type":"video","content_id":"389178879","content_offset_seconds":11911.998,"commenter":{"display_name":"ebaron13","_id":"200190112","name":"ebaron13","type":"user","bio":null,"created_at":"2018-03-01T23:14:01.565582Z","updated_at":"2019-01-11T23:33:49.901495Z","logo":"https://static-cdn.jtvnw.net/user-default-pictures/0ecbb6c3-fecb-4016-8115-aa467b7c36ed-profile_image-300x300.jpg"},"source":"chat","state":"published","message":{"body":"Kapp","fragments":[{"text":"Kapp"}],"is_action":false,"user_badges":[{"_id":"subscriber","version":"6"}],"user_color":"#FF0000"},"more_replies":false}],"_prev":"eyJpZCI6IjA4ZWNjNWRjLWNhOTctNGQzNC04MWRhLWFmMjk3MzgzY2Q2MiIsImhrIjoiYnJvYWRjYXN0OjMyOTk4MTQ3MDQwIiwic2siOiJBQUFLemFBdTRBQVZpRDNvb1FCakFBIn0b","_next":"eyJpZCI6IjlkNTA2NGQ3LTg3NzctNDgxYS1hZDFjLWE5YTU1MTYzZTM4ZCIsImhrIjoiYnJvYWRjYXN0OjMyOTk4MTQ3MDQwIiwic2siOiJBQUFLMVhwb3k0QVZpRDN3ZXpwT2dBIn0f"}